fscode/__init__.py
fscode/fscode.py
fscode/plan.py
pyfscode-2.0.0.dist-info/WHEEL
pyfscode-2.0.0.dist-info/entry_points.txt
pyfscode-2.0.0.dist-info/METADATA
pyfscode-2.0.0.dist-info/RECORD
