Metadata-Version: 2.3
Name: pyfscode
Version: 2.0.0
Summary: Filename Studio Code
Author: Bit0r
Author-email: Bit0r <nie_wang@outlook.com>
Requires-Dist: fire
Requires-Dist: plumbum
Requires-Dist: rich
Requires-Dist: fastnanoid
Requires-Dist: more-itertools
Requires-Dist: networkx
Requires-Python: >=3.13
